metonic/__init__.py
metonic/__version__.py
metonic/metonic.py
metonic_cycle-0.0.1.dist-info/LICENSE
metonic_cycle-0.0.1.dist-info/METADATA
metonic_cycle-0.0.1.dist-info/WHEEL
metonic_cycle-0.0.1.dist-info/top_level.txt
metonic_cycle-0.0.1.dist-info/RECORD
