Metadata-Version: 2.1
Name: metonic-cycle
Version: 0.0.1
Summary: Metonic cycle generator
Home-page: https://github.com/seanredmond/metonic
Author: Sean Redmond
Author-email: github-smr@sneakemail.com
Project-URL: Bug Tracker, https://github.com/seanredmond/metonic/issues
Classifier: Programming Language :: Python :: 3
Classifier: License :: OSI Approved :: GNU General Public License v3 or later (GPLv3+)
Classifier: Operating System :: OS Independent
Requires-Python: >=3.8
License-File: LICENSE
